{
  "block_number": 60,
  "created_at": "2026-06-26T01:00:04.896366",
  "hash": "bb8fc52b49a72859c00073b5ae8e32a972ec127ca51807262791b4dba9f22a51",
  "match": {
    "group_name": "Grupo D",
    "id": 24,
    "kickoff_time": "2026-06-26T02:00:00",
    "round": "Dia 15",
    "stage": "Group Stage",
    "team1_name": "Paraguai",
    "team2_name": "Austrália"
  },
  "payload": [
    {
      "goals_team1": 1,
      "goals_team2": 2,
      "username": "donfredoncarica"
    },
    {
      "goals_team1": 1,
      "goals_team2": 1,
      "username": "CLARA MARIA ALVES BEZERRA"
    },
    {
      "goals_team1": 1,
      "goals_team2": 1,
      "username": "danieloliveira"
    },
    {
      "goals_team1": 1,
      "goals_team2": 1,
      "username": "Ederlss"
    },
    {
      "goals_team1": 1,
      "goals_team2": 1,
      "username": "Ismael Tedesco"
    },
    {
      "goals_team1": 1,
      "goals_team2": 1,
      "username": "GLIVANUNES"
    },
    {
      "goals_team1": 2,
      "goals_team2": 1,
      "username": "MauroEvangelista"
    },
    {
      "goals_team1": 2,
      "goals_team2": 0,
      "username": "Paulomendonca13"
    },
    {
      "goals_team1": 2,
      "goals_team2": 0,
      "username": "marcos.melo"
    },
    {
      "goals_team1": 0,
      "goals_team2": 0,
      "username": "rodriguinho"
    },
    {
      "goals_team1": 2,
      "goals_team2": 1,
      "username": "felipedario"
    },
    {
      "goals_team1": 1,
      "goals_team2": 1,
      "username": "Humbertorps"
    },
    {
      "goals_team1": 1,
      "goals_team2": 2,
      "username": "mattheusf18"
    },
    {
      "goals_team1": 1,
      "goals_team2": 1,
      "username": "Erikatextor"
    },
    {
      "goals_team1": 1,
      "goals_team2": 0,
      "username": "Joviliano"
    },
    {
      "goals_team1": 1,
      "goals_team2": 1,
      "username": "tbastos"
    },
    {
      "goals_team1": 0,
      "goals_team2": 2,
      "username": "tsi"
    },
    {
      "goals_team1": 5,
      "goals_team2": 4,
      "username": "mestrejoel"
    },
    {
      "goals_team1": 1,
      "goals_team2": 0,
      "username": "marcelotole"
    },
    {
      "goals_team1": 2,
      "goals_team2": 1,
      "username": "tcavalcantebarros@gmail.com"
    },
    {
      "goals_team1": 2,
      "goals_team2": 1,
      "username": "fabiano"
    },
    {
      "goals_team1": 2,
      "goals_team2": 1,
      "username": "SergioGoncalves"
    },
    {
      "goals_team1": 1,
      "goals_team2": 1,
      "username": "alexandreeabra"
    },
    {
      "goals_team1": 2,
      "goals_team2": 1,
      "username": "esequiaspierre"
    },
    {
      "goals_team1": 2,
      "goals_team2": 1,
      "username": "daviahn"
    },
    {
      "goals_team1": 2,
      "goals_team2": 0,
      "username": "atcasanova"
    },
    {
      "goals_team1": 2,
      "goals_team2": 0,
      "username": "italloneves"
    },
    {
      "goals_team1": 1,
      "goals_team2": 1,
      "username": "leolenza"
    },
    {
      "goals_team1": 2,
      "goals_team2": 1,
      "username": "Francisco Ribeiro"
    },
    {
      "goals_team1": 1,
      "goals_team2": 0,
      "username": "leandraodamassa"
    },
    {
      "goals_team1": 1,
      "goals_team2": 2,
      "username": "Fernanda Rosa Gomes"
    },
    {
      "goals_team1": 1,
      "goals_team2": 1,
      "username": "CarlosRodrigoLima"
    },
    {
      "goals_team1": 2,
      "goals_team2": 1,
      "username": "Andrigo"
    },
    {
      "goals_team1": 1,
      "goals_team2": 2,
      "username": "Ismaellacerda"
    },
    {
      "goals_team1": 1,
      "goals_team2": 1,
      "username": "Leandro Moreira da Silva"
    },
    {
      "goals_team1": 0,
      "goals_team2": 0,
      "username": "ronilson"
    },
    {
      "goals_team1": 0,
      "goals_team2": 2,
      "username": "Ariadne"
    },
    {
      "goals_team1": 1,
      "goals_team2": 0,
      "username": "Daiany"
    },
    {
      "goals_team1": 1,
      "goals_team2": 0,
      "username": "Jota"
    },
    {
      "goals_team1": 1,
      "goals_team2": 1,
      "username": "vitorouab"
    },
    {
      "goals_team1": 1,
      "goals_team2": 2,
      "username": "paulofernandes"
    },
    {
      "goals_team1": 2,
      "goals_team2": 0,
      "username": "EDUARDO SALINAS"
    },
    {
      "goals_team1": 2,
      "goals_team2": 1,
      "username": "Catia Gontijo Rezende"
    },
    {
      "goals_team1": 1,
      "goals_team2": 1,
      "username": "welsinner"
    },
    {
      "goals_team1": 2,
      "goals_team2": 1,
      "username": "CathLuna"
    },
    {
      "goals_team1": 0,
      "goals_team2": 2,
      "username": "Angela Clara"
    },
    {
      "goals_team1": 1,
      "goals_team2": 2,
      "username": "Eunides"
    },
    {
      "goals_team1": 1,
      "goals_team2": 1,
      "username": "FelipeLopes"
    },
    {
      "goals_team1": 2,
      "goals_team2": 0,
      "username": "LeonardoRibeiro"
    },
    {
      "goals_team1": 2,
      "goals_team2": 0,
      "username": "Carlos Pilla"
    },
    {
      "goals_team1": 1,
      "goals_team2": 2,
      "username": "Bruno Anacleto"
    },
    {
      "goals_team1": 2,
      "goals_team2": 0,
      "username": "hugoalm"
    },
    {
      "goals_team1": 1,
      "goals_team2": 2,
      "username": "fernanda"
    },
    {
      "goals_team1": 1,
      "goals_team2": 0,
      "username": "Raphael Pecly"
    },
    {
      "goals_team1": 1,
      "goals_team2": 2,
      "username": "rafaelcabral"
    },
    {
      "goals_team1": 1,
      "goals_team2": 2,
      "username": "achaves"
    },
    {
      "goals_team1": 2,
      "goals_team2": 1,
      "username": "Sobrosa"
    },
    {
      "goals_team1": 2,
      "goals_team2": 1,
      "username": "Wallyaonreis"
    },
    {
      "goals_team1": 0,
      "goals_team2": 1,
      "username": "Marcia santos"
    },
    {
      "goals_team1": 2,
      "goals_team2": 0,
      "username": "Wescley"
    },
    {
      "goals_team1": 0,
      "goals_team2": 2,
      "username": "ivandro"
    },
    {
      "goals_team1": 2,
      "goals_team2": 1,
      "username": "sampaio"
    },
    {
      "goals_team1": 1,
      "goals_team2": 1,
      "username": "Fekilis"
    },
    {
      "goals_team1": 2,
      "goals_team2": 1,
      "username": "tiagoarrais"
    },
    {
      "goals_team1": 0,
      "goals_team2": 2,
      "username": "André Agatte"
    },
    {
      "goals_team1": 2,
      "goals_team2": 1,
      "username": "pfpastore"
    },
    {
      "goals_team1": 1,
      "goals_team2": 0,
      "username": "ERMES"
    },
    {
      "goals_team1": 1,
      "goals_team2": 1,
      "username": "luciano_pavao_"
    },
    {
      "goals_team1": 2,
      "goals_team2": 0,
      "username": "daniel.fernandes"
    },
    {
      "goals_team1": 2,
      "goals_team2": 1,
      "username": "Nilva veiga"
    },
    {
      "goals_team1": 1,
      "goals_team2": 1,
      "username": "LoganHelsing"
    },
    {
      "goals_team1": 1,
      "goals_team2": 2,
      "username": "Fjscorrea"
    },
    {
      "goals_team1": 2,
      "goals_team2": 1,
      "username": "Joao Paulo"
    },
    {
      "goals_team1": 1,
      "goals_team2": 0,
      "username": "Guilherme"
    },
    {
      "goals_team1": 1,
      "goals_team2": 2,
      "username": "helder"
    }
  ],
  "previous_hash": "4771f7da8e25a24086def1006ccedd316a0e8bb390df630b7d2f25b3cd217f1b",
  "schema": "bolao-copa-2026.audit-block.v1",
  "verification": {
    "algorithm": "SHA-256",
    "canonical_payload": "json.dumps(payload, sort_keys=True, separators=(',', ':'))",
    "input": "canonical_payload + previous_hash"
  }
}